{
  "list": ["LW", "FW", "RW", "LCM", "CM", "RCM", "LB", "CB", "RB", "", "GK", ""],
  "homeList": ["", "GK", "", "LB", "CB", "RB", "LCM", "CM", "RCM", "LW", "FW", "RW"],
  "awayList": ["LW", "FW", "RW", "LCM", "CM", "RCM", "LB", "CB", "RB", "", "GK", ""],
  "benchList": ["bench1", "bench2", "bench3"],
  "basicPostion": {
    "Home": {
      "LW": "",
      "FW": "",
      "RW": "",
      "LCM": "",
      "CM": "",
      "RCM": "",
      "LB": "",
      "CB": "",
      "RB": "",
      "GK": "",
      "bench1": "",
      "bench2": "",
      "bench3": ""
    },
    "Away": {
      "LW": "",
      "FW": "",
      "RW": "",
      "LCM": "",
      "CM": "",
      "RCM": "",
      "LB": "",
      "CB": "",
      "RB": "",
      "GK": "",
      "bench1": "",
      "bench2": "",
      "bench3": ""
    }
  },
  "homePosition": {

  }
}